__init__.py
server.py
tencentcloud_live_mcp_server-1.1.0.dist-info/licenses/LICENSE
tools/__init__.py
tools/live_api.py
utils/__init__.py
utils/config.py
utils/logger.py
utils/tencent_client.py
tencentcloud_live_mcp_server-1.1.0.dist-info/METADATA
tencentcloud_live_mcp_server-1.1.0.dist-info/WHEEL
tencentcloud_live_mcp_server-1.1.0.dist-info/entry_points.txt
tencentcloud_live_mcp_server-1.1.0.dist-info/top_level.txt
tencentcloud_live_mcp_server-1.1.0.dist-info/RECORD
