Metadata-Version: 2.4
Name: tencentcloud-live-mcp-server
Version: 1.1.0
Summary: Tencent Cloud API server implemented based on Model Context Protocol (MCP)
Author-email: willsygao <shuoyuan.gao0102@gmail.com>
Maintainer-email: willsygao <shuoyuan.gao0102@gmail.com>
License-Expression: MIT
Project-URL: Homepage, https://github.com/willsygao/tencentcloud-live-mcp-server
Project-URL: Repository, https://github.com/willsygao/tencentcloud-live-mcp-server.git
Requires-Python: >=3.12
License-File: LICENSE
Requires-Dist: tencentcloud-sdk-python>=3.0.0
Requires-Dist: requests>=2.32.3
Requires-Dist: mcp>=1.6.0
Dynamic: license-file
